bilma/__init__.py
bilma/bilma_model.py
bilma/preprocessing.py
bilma/transformer_text.py
bilma/wordpiece_tokenizer.py
bilma/resources/vocab_file_ALL.txt
bilma/test/bilma_demo.py
bilma-0.1.11.dist-info/LICENSE
bilma-0.1.11.dist-info/METADATA
bilma-0.1.11.dist-info/WHEEL
bilma-0.1.11.dist-info/top_level.txt
bilma-0.1.11.dist-info/RECORD
