Metadata-Version: 2.1
Name: bilma
Version: 0.1.11
Summary: A BERT implementation for twitter in Spanish.
Home-page: https://github.com/msubrayada/bilma
Author: Guillermo Ruiz
Author-email: lgruiz@centrogeo.edu.mx
Project-URL: Bug Reports, https://github.com/msubrayada/bilma/issues
Classifier: Development Status :: 3 - Alpha
Classifier: Intended Audience :: Science/Research
Classifier: Topic :: Scientific/Engineering :: Artificial Intelligence
Classifier: License :: OSI Approved :: MIT License
Classifier: Programming Language :: Python :: 3
License-File: LICENSE
